test_run_dir/AsyncResetTester/2021070521373913206516807100697855/AsyncResetTester.v
module AsyncResetTester(
  input   clock,
  input   reset
);
`ifdef RANDOMIZE_REG_INIT
  reg [31:0] _RAND_0;
  reg [31:0] _RAND_1;
  reg [31:0] _RAND_2;
  reg [31:0] _RAND_3;
`endif // RANDOMIZE_REG_INIT
  reg [1:0] cDiv_value; // @[Counter.scala 60:40]
  wire [1:0] _cDiv_wrap_value_T_1 = cDiv_value + 2'h1; // @[Counter.scala 76:24]
  wire  slowClk = cDiv_value == 2'h3; // @[AsyncResetSpec.scala 14:22]
  reg [3:0] count; // @[Counter.scala 60:40]
  wire  wrap_wrap = count == 4'hf; // @[Counter.scala 72:24]
  wire [3:0] _wrap_value_T_1 = count + 4'h1; // @[Counter.scala 76:24]
  reg  asyncResetNext; // @[AsyncResetSpec.scala 18:31]
  reg [7:0] reg_; // @[AsyncResetSpec.scala 23:12]
  wire  _T = count == 4'h3; // @[AsyncResetSpec.scala 27:15]
  wire  _T_4 = ~(reg_ == 8'h5 | reset); // @[AsyncResetSpec.scala 28:11]
  wire  _T_7 = count >= 4'h5 & count < 4'h7; // @[AsyncResetSpec.scala 30:22]
  wire  _T_12 = count >= 4'h7; // @[AsyncResetSpec.scala 32:22]
  always @(posedge clock) begin
    if (reset) begin // @[Counter.scala 60:40]
      cDiv_value <= 2'h0; // @[Counter.scala 60:40]
    end else begin
      cDiv_value <= _cDiv_wrap_value_T_1;
    end
    if (reset) begin // @[Counter.scala 60:40]
      count <= 4'h0; // @[Counter.scala 60:40]
    end else begin
      count <= _wrap_value_T_1;
    end
    if (reset) begin // @[AsyncResetSpec.scala 18:31]
      asyncResetNext <= 1'h0; // @[AsyncResetSpec.scala 18:31]
    end else begin
      asyncResetNext <= count == 4'h4; // @[AsyncResetSpec.scala 19:18]
    end
    `ifndef SYNTHESIS
    `ifdef PRINTF_COND
      if (`PRINTF_COND) begin
    `endif
        if (_T & ~(reg_ == 8'h5 | reset)) begin
          $fwrite(32'h80000002,"Assertion failed\n    at AsyncResetSpec.scala:28 assert(reg === 5.U)\n"); // @[AsyncResetSpec.scala 28:11]
        end
    `ifdef PRINTF_COND
      end
    `endif
    `endif // SYNTHESIS
    `ifndef SYNTHESIS
    `ifdef STOP_COND
      if (`STOP_COND) begin
    `endif
        if (_T & ~(reg_ == 8'h5 | reset)) begin
          $fatal; // @[AsyncResetSpec.scala 28:11]
        end
    `ifdef STOP_COND
      end
    `endif
    `endif // SYNTHESIS
    `ifndef SYNTHESIS
    `ifdef PRINTF_COND
      if (`PRINTF_COND) begin
    `endif
        if (_T_7 & ~(reg_ == 8'h7b | reset)) begin
          $fwrite(32'h80000002,"Assertion failed\n    at AsyncResetSpec.scala:31 assert(reg === 123.U)\n"); // @[AsyncResetSpec.scala 31:11]
        end
    `ifdef PRINTF_COND
      end
    `endif
    `endif // SYNTHESIS
    `ifndef SYNTHESIS
    `ifdef STOP_COND
      if (`STOP_COND) begin
    `endif
        if (_T_7 & ~(reg_ == 8'h7b | reset)) begin
          $fatal; // @[AsyncResetSpec.scala 31:11]
        end
    `ifdef STOP_COND
      end
    `endif
    `endif // SYNTHESIS
    `ifndef SYNTHESIS
    `ifdef PRINTF_COND
      if (`PRINTF_COND) begin
    `endif
        if (~_T_7 & _T_12 & _T_4) begin
          $fwrite(32'h80000002,"Assertion failed\n    at AsyncResetSpec.scala:33 assert(reg === 5.U)\n"); // @[AsyncResetSpec.scala 33:11]
        end
    `ifdef PRINTF_COND
      end
    `endif
    `endif // SYNTHESIS
    `ifndef SYNTHESIS
    `ifdef STOP_COND
      if (`STOP_COND) begin
    `endif
        if (~_T_7 & _T_12 & _T_4) begin
          $fatal; // @[AsyncResetSpec.scala 33:11]
        end
    `ifdef STOP_COND
      end
    `endif
    `endif // SYNTHESIS
    `ifndef SYNTHESIS
    `ifdef STOP_COND
      if (`STOP_COND) begin
    `endif
        if (wrap_wrap & ~reset) begin
          $finish; // @[AsyncResetSpec.scala 37:9]
        end
    `ifdef STOP_COND
      end
    `endif
    `endif // SYNTHESIS
  end
  always @(posedge slowClk or posedge asyncResetNext) begin
    if (asyncResetNext) begin
      reg_ <= 8'h7b;
    end else begin
      reg_ <= 8'h5;
    end
  end
// Register and memory initialization
`ifdef RANDOMIZE_GARBAGE_ASSIGN
`define RANDOMIZE
`endif
`ifdef RANDOMIZE_INVALID_ASSIGN
`define RANDOMIZE
`endif
`ifdef RANDOMIZE_REG_INIT
`define RANDOMIZE
`endif
`ifdef RANDOMIZE_MEM_INIT
`define RANDOMIZE
`endif
`ifndef RANDOM
`define RANDOM $random
`endif
`ifdef RANDOMIZE_MEM_INIT
  integer initvar;
`endif
`ifndef SYNTHESIS
`ifdef FIRRTL_BEFORE_INITIAL
`FIRRTL_BEFORE_INITIAL
`endif
initial begin
  `ifdef RANDOMIZE
    `ifdef INIT_RANDOM
      `INIT_RANDOM
    `endif
    `ifndef VERILATOR
      `ifdef RANDOMIZE_DELAY
        #`RANDOMIZE_DELAY begin end
      `else
        #0.002 begin end
      `endif
    `endif
`ifdef RANDOMIZE_REG_INIT
  _RAND_0 = {1{`RANDOM}};
  cDiv_value = _RAND_0[1:0];
  _RAND_1 = {1{`RANDOM}};
  count = _RAND_1[3:0];
  _RAND_2 = {1{`RANDOM}};
  asyncResetNext = _RAND_2[0:0];
  _RAND_3 = {1{`RANDOM}};
  reg_ = _RAND_3[7:0];
`endif // RANDOMIZE_REG_INIT
  if (asyncResetNext) begin
    reg_ = 8'h7b;
  end
  `endif // RANDOMIZE
end // initial
`ifdef FIRRTL_AFTER_INITIAL
`FIRRTL_AFTER_INITIAL
`endif
`endif // SYNTHESIS
endmodule

test_run_dir/AsyncResetTester/2021070521373913206516807100697855/dump.vcd
$version Generated by VerilatedVcd $end
$date Mon Jul  5 21:37:41 2021 $end
$timescale 1ps $end

 $scope module TOP $end
  $var wire  1 & clock $end
  $var wire  1 ' reset $end
  $scope module AsyncResetTester $end
   $var wire  1 % asyncResetNext $end
   $var wire  2 ( cDiv_value [1:0] $end
   $var wire  1 & clock $end
   $var wire  4 # count [3:0] $end
   $var wire  8 * reg_ [7:0] $end
   $var wire  1 ' reset $end
   $var wire  1 ) slowClk $end
   $var wire  1 $ wrap_wrap $end
  $upscope $end
 $upscope $end
$enddefinitions $end


#0
b0000 #
0$
0%
0&
1'
b00 (
0)
b00000000 *
#1
1&
#2
#3
#4
#5
#6
0&
#7
#8
#9
#10
0'
#11
b0001 #
1&
b01 (
#12
#13
#14
#15
#16
0&
#17
#18
#19
#20
#21
b0010 #
1&
b10 (
#22
#23
#24
#25
#26
0&
#27
#28
#29
#30
#31
b0011 #
1&
b11 (
1)
b00000101 *
#32
#33
#34
#35
#36
0&
#37
#38
#39
#40
#41
b0100 #
1&
b00 (
0)
#42
#43
#44
#45
#46
0&
#47
#48
#49
#50
#51
b0101 #
1%
1&
b01 (
b01111011 *
#52
#53
#54
#55
#56
0&
#57
#58
#59
#60
#61
b0110 #
0%
1&
b10 (
#62
#63
#64
#65
#66
0&
#67
#68
#69
#70
#71
b0111 #
1&
b11 (
1)
b00000101 *
#72
#73
#74
#75
#76
0&
#77
#78
#79
#80
#81
b1000 #
1&
b00 (
0)
#82
#83
#84
#85
#86
0&
#87
#88
#89
#90
#91
b1001 #
1&
b01 (
#92
#93
#94
#95
#96
0&
#97
#98
#99
#100
#101
b1010 #
1&
b10 (
#102
#103
#104
#105
#106
0&
#107
#108
#109
#110
#111
b1011 #
1&
b11 (
1)
#112
#113
#114
#115
#116
0&
#117
#118
#119
#120
#121
b1100 #
1&
b00 (
0)
#122
#123
#124
#125
#126
0&
#127
#128
#129
#130
#131
b1101 #
1&
b01 (
#132
#133
#134
#135
#136
0&
#137
#138
#139
#140
#141
b1110 #
1&
b10 (
#142
#143
#144
#145
#146
0&
#147
#148
#149
#150
#151
b1111 #
1$
1&
b11 (
1)
